cstriggers/__init__.py
cstriggers/core/__init__.py
cstriggers/core/constants.py
cstriggers/core/helper.py
cstriggers/core/parser.py
cstriggers/core/test.py
cstriggers/core/trigger.py
cron_schedule_triggers_fishy-0.0.11.dist-info/METADATA
cron_schedule_triggers_fishy-0.0.11.dist-info/WHEEL
cron_schedule_triggers_fishy-0.0.11.dist-info/top_level.txt
cron_schedule_triggers_fishy-0.0.11.dist-info/RECORD
